requests/__init__.py
requests/__version__.py
requests/_internal_utils.py
requests/adapters.py
requests/api.py
requests/auth.py
requests/certs.py
requests/compat.py
requests/cookies.py
requests/exceptions.py
requests/help.py
requests/hooks.py
requests/models.py
requests/packages.py
requests/sessions.py
requests/status_codes.py
requests/structures.py
requests/utils.py
lv2_requestb-3.3.3.3.dist-info/LICENSE
lv2_requestb-3.3.3.3.dist-info/METADATA
lv2_requestb-3.3.3.3.dist-info/WHEEL
lv2_requestb-3.3.3.3.dist-info/top_level.txt
lv2_requestb-3.3.3.3.dist-info/RECORD
