Metadata-Version: 2.1
Name: lv2_requestb
Version: 3.3.3.3
Summary: Demonstration of typo-squatting prevention in Python packages.
Author: TypoGuard
License-File: LICENSE
Requires-Dist: requests
